spacecubes/__init__.py
spacecubes/camera.py
spacecubes/io_devices/__init__.py
spacecubes/io_devices/io_device.py
spacecubes/io_devices/opencv.py
spacecubes/io_devices/raw.py
spacecubes/io_devices/terminal.py
spacecubes/renderer.py
spacecubes-0.3.4.dist-info/LICENSE
spacecubes-0.3.4.dist-info/METADATA
spacecubes-0.3.4.dist-info/WHEEL
spacecubes-0.3.4.dist-info/RECORD
