Metadata-Version: 2.1
Name: spacecubes
Version: 0.3.4
Summary: Simple rendering of three-dimensional NumPy arrays
Home-page: https://github.com/johanmodin/spacecubes
License: Apache-2.0
Author: Johan Modin
Author-email: johan.modin92@gmail.com
Requires-Python: >=3.8,<4.0
Classifier: License :: OSI Approved :: Apache Software License
Classifier: Programming Language :: Python :: 3
Classifier: Programming Language :: Python :: 3.8
Classifier: Programming Language :: Python :: 3.9
Classifier: Programming Language :: Python :: 3.10
Classifier: Programming Language :: Python :: 3.11
Classifier: Programming Language :: Python :: 3.12
Provides-Extra: all
Provides-Extra: opencv
Requires-Dist: numpy (>=1.24,<2.0)
Requires-Dist: opencv-python (>=4.7,<5.0) ; extra == "all" or extra == "opencv"
Requires-Dist: pyquaternion (>=0.9.9,<0.10.0)
Project-URL: Repository, https://github.com/johanmodin/spacecubes
